{
   "id": 1,
   "name": "roni Tebul",
   "quiz": [
      { "questionId": 0, "answerId": 1 },
      { "questionId": 1, "answerId": 2 },
      { "questionId": 2, "answerId": 2 },
      { "questionId": 3, "answerId": 4 }
   ],
   "friends": [
      {
         "id": 0,
         "name": "Romi",
         "quiz": [
            { "questionId": 0, "answerId": 1 },
            { "questionId": 1, "answerId": 1 },
            { "questionId": 2, "answerId": 2 },
            { "questionId": 3, "answerId": 4 }
         ],
         "rightAnswers": 3
      },
      {
         "id": 1,
         "name": "Jenni",
         "quiz": [
            { "questionId": 0, "answerId": 1 },
            { "questionId": 1, "answerId": 2 },
            { "questionId": 2, "answerId": 2 },
            { "questionId": 3, "answerId": 4 }
         ],
         "rightAnswers": 4
      },
      {
         "id": 2,
         "name": "Bad friend",
         "quiz": [
            { "questionId": 0, "answerId": 3 },
            { "questionId": 1, "answerId": 3 },
            { "questionId": 2, "answerId": 3 },
            { "questionId": 3, "answerId": 3 }
         ],
         "rightAnswers": 0
      }
   ]
}
